{
  "_format": "hh-sol-cache-2",
  "files": {
    "D:\\CODING\\React Js\\Document-Verification\\blockchain\\contracts\\CertificateValidator.sol": {
      "lastModificationDate": 1772177459317,
      "contentHash": "2a256eb1477e58ba86edb869b978b0aa",
      "sourceName": "contracts/CertificateValidator.sol",
      "solcConfig": {
        "version": "0.8.20",
        "settings": {
          "optimizer": {
            "enabled": true,
            "runs": 200
          },
          "evmVersion": "paris",
          "outputSelection": {
            "*": {
              "*": [
                "abi",
                "evm.bytecode",
                "evm.deployedBytecode",
                "evm.methodIdentifiers",
                "metadata"
              ],
              "": [
                "ast"
              ]
            }
          }
        }
      },
      "imports": [],
      "versionPragmas": [
        "^0.8.20"
      ],
      "artifacts": [
        "CertificateValidator"
      ]
    },
    "D:\\CODING\\React Js\\Test Folder\\Document-Verification\\blockchain\\contracts\\CertificateValidator.sol": {
      "lastModificationDate": 1772637621142,
      "contentHash": "2a256eb1477e58ba86edb869b978b0aa",
      "sourceName": "contracts/CertificateValidator.sol",
      "solcConfig": {
        "version": "0.8.20",
        "settings": {
          "optimizer": {
            "enabled": true,
            "runs": 200
          },
          "evmVersion": "paris",
          "outputSelection": {
            "*": {
              "*": [
                "abi",
                "evm.bytecode",
                "evm.deployedBytecode",
                "evm.methodIdentifiers",
                "metadata"
              ],
              "": [
                "ast"
              ]
            }
          }
        }
      },
      "imports": [],
      "versionPragmas": [
        "^0.8.20"
      ],
      "artifacts": [
        "CertificateValidator"
      ]
    }
  }
}
